{
  "status": "success",
  "data": [
    {
      "_id": "582945984ea3b4ce5c3ff6bf",
      "globalsupplierId": 1,
      "globalsupplierType": "semi",
      "globalsuppliername": "atoz",
      "globalsupplierDesc": "Supplies chillies from all over India",
      "globalSupplierRatings": "b+",
      "gobalsupplierlist": [
        "aaa",
        "bbb",
        "ccc"
      ],
      "leadGraph": [
        "aaa",
        "bbb",
        "ccc",
        "ddd",
        "fff"
      ],
      "operation": "aa",
      "factoryProperties": {
        "measure": "bbb",
        "rooms": "ccc",
        "size": "hhh",
        "contracts1": "iii",
        "contract2": "jjj",
        "contracts3": "kkk",
        "contractsList": [
          "lll",
          "mmm"
        ],
        "contractsLock": [
          "nnn",
          "ooo",
          "ppp",
          "qqq",
          "rrr"
        ],
        "approvals": [
          "sss",
          "ttt",
          "uuu"
        ],
        "comms": {
          "tel": "vvv",
          "tel2": "vvv",
          "email": "vvv"
        }
      },
      "sizes": [
        {
          "roomType": "www",
          "firstLevel": [
            "xxx",
            "yyy",
            "zzz"
          ],
          "secondLevel": [
            "aaaa",
            "bbbb",
            "cccc"
          ],
          "thirdLevel": [
            "llll",
            "llll",
            "llll"
          ]
        },
        {
          "roomType": "eeee",
          "firstLevel": [
            "ffff",
            "gggg",
            "hhhh"
          ],
          "secondLevel": [
            "iiii",
            "jjjj",
            "kkkk"
          ],
          "thirdLevel": [
            "llll",
            "llll",
            "llll"
          ]
        },
        {
          "roomType": "hhh",
          "firstLevel": [
            "mmmm",
            "nnnn",
            "oooo"
          ],
          "secondLevel": [
            "pppp",
            "qqqq",
            "rrrr"
          ],
          "thirdLevel": [
            "llll",
            "llll",
            "llll"
          ]
        }
      ],
      "agents": {
        "agentLocation": "ssss",
        "agentTimeZone": "tttt",
        "agentQuality": "uuuu",
        "agentAvailability": "vvvv",
        "agentBackup": "wwww",
        "agentComments": "xxxx",
        "agentVerified": "yyyy",
        "agentContacts": [
          {
            "contactType": "zzzz",
            "contacts": [
              "aaaaa",
              "bbbbb",
              "ccccc"
            ]
          },
          {
            "contactType": "zzzz",
            "contacts": [
              "aaaaa",
              "bbbbb",
              "ccccc"
            ]
          }
        ],
        "leadText": [
          "ddddd",
          "eeeee"
        ],
        "leadLevel": "fffff",
        "leadSuccess": "ggggg"
      },
      "leads": {
        "leadType": "hhhhh",
        "leadsList": [
          "iiiii",
          "jjjjj"
        ]
      },
      "mediators": [
        {
          "globalsupplierType": "raw",
          "globalsupplierIds": [
            2234,
            5535,
            5534
          ]
        },
        {
          "globalsupplierType": "earth",
          "globalsupplierIds": [
            3334,
            6635,
            8734
          ]
        },
        {
          "globalsupplierType": "assembly",
          "globalsupplierIds": [
            4434,
            7735,
            6734
          ]
        }
      ]
    },
    {
      "_id": "582bd58a87ff38c8660b879c",
      "globalsupplierId": 2,
      "globalsupplierType": "semi",
      "globalsuppliername": "North Star Suppliers",
      "globalsupplierDesc": "Chilli Supplier from North India",
      "globalSupplierRatings": "b+",
      "serviceOwners": [
        "aaa",
        "bbb",
        "ccc"
      ],
      "leadGraph": [
        "aaa",
        "bbb",
        "ccc",
        "ddd",
        "eee"
      ],
      "operation": "aa",
      "factoryProperties": {
        "measure": "bbb",
        "rooms": "ccc",
        "size": "hhh",
        "contracts1": "iii",
        "contract2": "jjj",
        "contracts3": "kkk",
        "contractsList": [
          "lll",
          "mmm"
        ],
        "contractsLock": [
          "nnn",
          "ooo",
          "ppp",
          "qqq",
          "rrr"
        ],
        "approvals": [
          "sss",
          "ttt",
          "uuu"
        ],
        "comms": {
          "tel": "vvv",
          "tel2": "vvv",
          "email": "vvv"
        }
      },
      "sizes": [
        {
          "roomType": "www",
          "firstLevel": [
            "xxx",
            "yyy",
            "zzz"
          ],
          "secondLevel": [
            "aaaa",
            "bbbb",
            "cccc"
          ],
          "thirdLevel": [
            "llll",
            "llll",
            "llll"
          ]
        },
        {
          "roomType": "eeee",
          "firstLevel": [
            "ffff",
            "gggg",
            "hhhh"
          ],
          "secondLevel": [
            "iiii",
            "jjjj",
            "kkkk"
          ],
          "thirdLevel": [
            "llll",
            "llll",
            "llll"
          ]
        },
        {
          "roomType": "hhh",
          "firstLevel": [
            "mmmm",
            "nnnn",
            "oooo"
          ],
          "secondLevel": [
            "pppp",
            "qqqq",
            "rrrr"
          ],
          "thirdLevel": [
            "llll",
            "llll",
            "llll"
          ]
        }
      ],
      "agents": {
        "agentLocation": "ssss",
        "agentTimeZone": "tttt",
        "agentQuality": "uuuu",
        "agentAvailability": "vvvv",
        "agentBackup": "wwww",
        "agentComments": "xxxx",
        "agentVerified": "yyyy",
        "agentContacts": [
          {
            "contactType": "zzzz",
            "contacts": [
              "aaaaa",
              "bbbbb",
              "ccccc"
            ]
          },
          {
            "contactType": "zzzz",
            "contacts": [
              "aaaaa",
              "bbbbb",
              "ccccc"
            ]
          }
        ],
        "leadText": [
          "ddddd",
          "eeeee"
        ],
        "leadLevel": "fffff",
        "leadSuccess": "ggggg"
      },
      "leads": {
        "leadType": "hhhhh",
        "leadsList": [
          "iiiii",
          "jjjjj"
        ]
      },
      "mediators": [
        {
          "globalsupplierType": "raw",
          "globalsupplierIds": [
            2234,
            5535,
            5534
          ]
        },
        {
          "globalsupplierType": "earth",
          "globalsupplierIds": [
            3334,
            6635,
            8734
          ]
        },
        {
          "globalsupplierType": "assembly",
          "globalsupplierIds": [
            4434,
            7735,
            6734
          ]
        }
      ]
    },
    {
      "_id": "582bf1c687ff38c8660b879d",
      "globalsupplierId": 3,
      "globalsupplierType": "semi",
      "globalsuppliername": "nanbns",
      "globalsupplierDesc": "jjiyuvv",
      "globalSupplierRatings": "b+",
      "serviceOwners": [
        "aaa",
        "bbb",
        "ccc"
      ],
      "leadGraph": [
        "aaa",
        "hhhuct",
        "falsdjfasdl",
        "jaskfjaslkdf",
        "nanbns"
      ],
      "operation": "aa",
      "factoryProperties": {
        "measure": "bbb",
        "rooms": "ccc",
        "size": "hhh",
        "contracts1": "iii",
        "contract2": "jjj",
        "contracts3": "kkk",
        "contractsList": [
          "lll",
          "mmm"
        ],
        "contractsLock": [
          "nnn",
          "ooo",
          "ppp",
          "qqq",
          "rrr"
        ],
        "approvals": [
          "sss",
          "ttt",
          "uuu"
        ],
        "comms": {
          "tel": "vvv",
          "tel2": "vvv",
          "email": "vvv"
        }
      },
      "sizes": [
        {
          "roomType": "www",
          "firstLevel": [
            "xxx",
            "yyy",
            "zzz"
          ],
          "secondLevel": [
            "aaaa",
            "bbbb",
            "cccc"
          ],
          "thirdLevel": [
            "llll",
            "llll",
            "llll"
          ]
        },
        {
          "roomType": "eeee",
          "firstLevel": [
            "ffff",
            "gggg",
            "hhhh"
          ],
          "secondLevel": [
            "iiii",
            "jjjj",
            "kkkk"
          ],
          "thirdLevel": [
            "llll",
            "llll",
            "llll"
          ]
        },
        {
          "roomType": "hhh",
          "firstLevel": [
            "mmmm",
            "nnnn",
            "oooo"
          ],
          "secondLevel": [
            "pppp",
            "qqqq",
            "rrrr"
          ],
          "thirdLevel": [
            "llll",
            "llll",
            "llll"
          ]
        }
      ],
      "agents": {
        "agentLocation": "ssss",
        "agentTimeZone": "tttt",
        "agentQuality": "uuuu",
        "agentAvailability": "vvvv",
        "agentBackup": "wwww",
        "agentComments": "xxxx",
        "agentVerified": "yyyy",
        "agentContacts": [
          {
            "contactType": "zzzz",
            "contacts": [
              "aaaaa",
              "bbbbb",
              "ccccc"
            ]
          },
          {
            "contactType": "zzzz",
            "contacts": [
              "aaaaa",
              "bbbbb",
              "ccccc"
            ]
          }
        ],
        "leadText": [
          "ddddd",
          "eeeee"
        ],
        "leadLevel": "fffff",
        "leadSuccess": "ggggg"
      },
      "leads": {
        "leadType": "hhhhh",
        "leadsList": [
          "iiiii",
          "jjjjj"
        ]
      },
      "mediators": [
        {
          "globalsupplierType": "raw",
          "globalsupplierIds": [
            2234,
            5535,
            5534
          ]
        },
        {
          "globalsupplierType": "earth",
          "globalsupplierIds": [
            3334,
            6635,
            8734
          ]
        },
        {
          "globalsupplierType": "assembly",
          "globalsupplierIds": [
            4434,
            7735,
            6734
          ]
        }
      ]
    },
    {
      "_id": "582c0b0387ff38c8660b87a1",
      "globalsupplierId": 4,
      "globalsupplierType": "semi",
      "globalsuppliername": "vertical zone",
      "globalsupplierDesc": "fjalsfdjalskdfj",
      "globalSupplierRatings": "b+",
      "serviceOwners": [
        "aaa",
        "bbb",
        "ccc"
      ],
      "leadGraph": [
        "aaa",
        "hhhuct",
        "falsdjfasdl",
        "jaskfjaslkdf",
        "fjasdfjl"
      ],
      "operation": "aa",
      "factoryProperties": {
        "measure": "bbb",
        "rooms": "ccc",
        "size": "hhh",
        "contracts1": "iii",
        "contract2": "jjj",
        "contracts3": "kkk",
        "contractsList": [
          "lll",
          "mmm"
        ],
        "contractsLock": [
          "nnn",
          "ooo",
          "ppp",
          "qqq",
          "rrr"
        ],
        "approvals": [
          "sss",
          "ttt",
          "uuu"
        ],
        "comms": {
          "tel": "vvv",
          "tel2": "vvv",
          "email": "vvv"
        }
      },
      "sizes": [
        {
          "roomType": "www",
          "firstLevel": [
            "xxx",
            "yyy",
            "zzz"
          ],
          "secondLevel": [
            "aaaa",
            "bbbb",
            "cccc"
          ],
          "thirdLevel": [
            "llll",
            "llll",
            "llll"
          ]
        },
        {
          "roomType": "eeee",
          "firstLevel": [
            "ffff",
            "gggg",
            "hhhh"
          ],
          "secondLevel": [
            "iiii",
            "jjjj",
            "kkkk"
          ],
          "thirdLevel": [
            "llll",
            "llll",
            "llll"
          ]
        },
        {
          "roomType": "hhh",
          "firstLevel": [
            "mmmm",
            "nnnn",
            "oooo"
          ],
          "secondLevel": [
            "pppp",
            "qqqq",
            "rrrr"
          ],
          "thirdLevel": [
            "llll",
            "llll",
            "llll"
          ]
        }
      ],
      "agents": {
        "agentLocation": "ssss",
        "agentTimeZone": "tttt",
        "agentQuality": "uuuu",
        "agentAvailability": "vvvv",
        "agentBackup": "wwww",
        "agentComments": "xxxx",
        "agentVerified": "yyyy",
        "agentContacts": [
          {
            "contactType": "zzzz",
            "contacts": [
              "aaaaa",
              "bbbbb",
              "ccccc"
            ]
          },
          {
            "contactType": "zzzz",
            "contacts": [
              "aaaaa",
              "bbbbb",
              "ccccc"
            ]
          }
        ],
        "leadText": [
          "ddddd",
          "eeeee"
        ],
        "leadLevel": "fffff",
        "leadSuccess": "ggggg"
      },
      "leads": {
        "leadType": "hhhhh",
        "leadsList": [
          "iiiii",
          "jjjjj"
        ]
      },
      "mediators": [
        {
          "globalsupplierType": "raw",
          "globalsupplierIds": [
            2234,
            5535,
            5534
          ]
        },
        {
          "globalsupplierType": "earth",
          "globalsupplierIds": [
            3334,
            6635,
            8734
          ]
        },
        {
          "globalsupplierType": "assembly",
          "globalsupplierIds": [
            4434,
            7735,
            6734
          ]
        }
      ]
    },
    {
      "_id": "582c0ba687ff38c8660b87a2",
      "globalsupplierId": 5,
      "globalsupplierType": "semi",
      "globalsuppliername": "Uppser Stalls",
      "globalsupplierDesc": "Competitive Upper Stall Pricing",
      "globalSupplierRatings": "b+",
      "serviceOwners": [
        "aaa",
        "bbb",
        "ccc"
      ],
      "leadGraph": [
        "aaa",
        "hhhuct",
        "falsdjfasdl",
        "Maintain hhhucts",
        "Maintain Alternatives"
      ],
      "operation": "aa",
      "factoryProperties": {
        "measure": "bbb",
        "rooms": "ccc",
        "size": "hhh",
        "contracts1": "iii",
        "contract2": "jjj",
        "contracts3": "kkk",
        "contractsList": [
          "lll",
          "mmm"
        ],
        "contractsLock": [
          "nnn",
          "ooo",
          "ppp",
          "qqq",
          "rrr"
        ],
        "approvals": [
          "sss",
          "ttt",
          "uuu"
        ],
        "comms": {
          "tel": "vvv",
          "tel2": "vvv",
          "email": "vvv"
        }
      },
      "sizes": [
        {
          "roomType": "www",
          "firstLevel": [
            "xxx",
            "yyy",
            "zzz"
          ],
          "secondLevel": [
            "aaaa",
            "bbbb",
            "cccc"
          ],
          "thirdLevel": [
            "llll",
            "llll",
            "llll"
          ]
        },
        {
          "roomType": "eeee",
          "firstLevel": [
            "ffff",
            "gggg",
            "hhhh"
          ],
          "secondLevel": [
            "iiii",
            "jjjj",
            "kkkk"
          ],
          "thirdLevel": [
            "llll",
            "llll",
            "llll"
          ]
        },
        {
          "roomType": "hhh",
          "firstLevel": [
            "mmmm",
            "nnnn",
            "oooo"
          ],
          "secondLevel": [
            "pppp",
            "qqqq",
            "rrrr"
          ],
          "thirdLevel": [
            "llll",
            "llll",
            "llll"
          ]
        }
      ],
      "agents": {
        "agentLocation": "ssss",
        "agentTimeZone": "tttt",
        "agentQuality": "uuuu",
        "agentAvailability": "vvvv",
        "agentBackup": "wwww",
        "agentComments": "xxxx",
        "agentVerified": "yyyy",
        "agentContacts": [
          {
            "contactType": "zzzz",
            "contacts": [
              "aaaaa",
              "bbbbb",
              "ccccc"
            ]
          },
          {
            "contactType": "zzzz",
            "contacts": [
              "aaaaa",
              "bbbbb",
              "ccccc"
            ]
          }
        ],
        "leadText": [
          "ddddd",
          "eeeee"
        ],
        "leadLevel": "fffff",
        "leadSuccess": "ggggg"
      },
      "leads": {
        "leadType": "hhhhh",
        "leadsList": [
          "iiiii",
          "jjjjj"
        ]
      },
      "mediators": [
        {
          "globalsupplierType": "raw",
          "globalsupplierIds": [
            2234,
            5535,
            5534
          ]
        },
        {
          "globalsupplierType": "earth",
          "globalsupplierIds": [
            3334,
            6635,
            8734
          ]
        },
        {
          "globalsupplierType": "assembly",
          "globalsupplierIds": [
            4434,
            7735,
            6734
          ]
        }
      ]
    },
    {
      "_id": "582c0c1087ff38c8660b87a3",
      "globalsupplierId": 6,
      "globalsupplierType": "semi",
      "globalsuppliername": "Pure Play Exports",
      "globalsupplierDesc": "Cheap and Honest Pricing",
      "globalSupplierRatings": "b+",
      "serviceOwners": [
        "aaa",
        "bbb",
        "ccc"
      ],
      "leadGraph": [
        "aaa",
        "hhhuct",
        "falsdjfasdl",
        "Adjunct Company",
        "Pure Play Exports"
      ],
      "operation": "aa",
      "factoryProperties": {
        "measure": "bbb",
        "rooms": "ccc",
        "size": "hhh",
        "contracts1": "iii",
        "contract2": "jjj",
        "contracts3": "kkk",
        "contractsList": [
          "lll",
          "mmm"
        ],
        "contractsLock": [
          "nnn",
          "ooo",
          "ppp",
          "qqq",
          "rrr"
        ],
        "approvals": [
          "sss",
          "ttt",
          "uuu"
        ],
        "comms": {
          "tel": "vvv",
          "tel2": "vvv",
          "email": "vvv"
        }
      },
      "sizes": [
        {
          "roomType": "www",
          "firstLevel": [
            "xxx",
            "yyy",
            "zzz"
          ],
          "secondLevel": [
            "aaaa",
            "bbbb",
            "cccc"
          ],
          "thirdLevel": [
            "llll",
            "llll",
            "llll"
          ]
        },
        {
          "roomType": "eeee",
          "firstLevel": [
            "ffff",
            "gggg",
            "hhhh"
          ],
          "secondLevel": [
            "iiii",
            "jjjj",
            "kkkk"
          ],
          "thirdLevel": [
            "llll",
            "llll",
            "llll"
          ]
        },
        {
          "roomType": "hhh",
          "firstLevel": [
            "mmmm",
            "nnnn",
            "oooo"
          ],
          "secondLevel": [
            "pppp",
            "qqqq",
            "rrrr"
          ],
          "thirdLevel": [
            "llll",
            "llll",
            "llll"
          ]
        }
      ],
      "agents": {
        "agentLocation": "ssss",
        "agentTimeZone": "tttt",
        "agentQuality": "uuuu",
        "agentAvailability": "vvvv",
        "agentBackup": "wwww",
        "agentComments": "xxxx",
        "agentVerified": "yyyy",
        "agentContacts": [
          {
            "contactType": "zzzz",
            "contacts": [
              "aaaaa",
              "bbbbb",
              "ccccc"
            ]
          },
          {
            "contactType": "zzzz",
            "contacts": [
              "aaaaa",
              "bbbbb",
              "ccccc"
            ]
          }
        ],
        "leadText": [
          "ddddd",
          "eeeee"
        ],
        "leadLevel": "fffff",
        "leadSuccess": "ggggg"
      },
      "leads": {
        "leadType": "hhhhh",
        "leadsList": [
          "iiiii",
          "jjjjj"
        ]
      },
      "mediators": [
        {
          "globalsupplierType": "raw",
          "globalsupplierIds": [
            2234,
            5535,
            5534
          ]
        },
        {
          "globalsupplierType": "earth",
          "globalsupplierIds": [
            3334,
            6635,
            8734
          ]
        },
        {
          "globalsupplierType": "assembly",
          "globalsupplierIds": [
            4434,
            7735,
            6734
          ]
        }
      ]
    }
  ]
}